newt
tests
