Metadata-Version: 2.1
Name: newt-transformer
Version: 0.1.7
Summary: Amphibious new data transformer to prepare various sources for CGP DSS Data Loader
Home-page: https://github.com/DataBiosphere/newt-transformer
Author: Jesse Brennan
Author-email: brennan@ucsc.edu
License: Apache License 2.0
Keywords: genomics,metadata,NIHDataCommons
Platform: UNKNOWN
Classifier: Development Status :: 3 - Alpha
Classifier: Intended Audience :: Science/Research
Classifier: License :: OSI Approved :: Apache Software License
Classifier: Natural Language :: English
Classifier: Programming Language :: Python :: 3.6
Classifier: Topic :: Scientific/Engineering :: Bio-Informatics
